README.md
setup.py
chemotaxis/__init__.py
chemotaxis/composites/__init__.py
chemotaxis/composites/chemotaxis_flagella.py
chemotaxis/composites/chemotaxis_master.py
chemotaxis/composites/chemotaxis_minimal.py
chemotaxis/composites/flagella_expression.py
chemotaxis/composites/transport_metabolism.py
chemotaxis/experiments/__init__.py
chemotaxis/experiments/control.py
chemotaxis/experiments/paper_experiments.py
chemotaxis/processes/__init__.py
chemotaxis/processes/chemoreceptor_cluster.py
chemotaxis/processes/coarse_motor.py
chemotaxis/processes/flagella_motor.py
chemotaxis/processes/membrane_potential.py
vivarium_chemotaxis.egg-info/PKG-INFO
vivarium_chemotaxis.egg-info/SOURCES.txt
vivarium_chemotaxis.egg-info/dependency_links.txt
vivarium_chemotaxis.egg-info/entry_points.txt
vivarium_chemotaxis.egg-info/requires.txt
vivarium_chemotaxis.egg-info/top_level.txt