Metadata-Version: 2.1
Name: vivarium-chemotaxis
Version: 0.0.2
Summary: UNKNOWN
Home-page: https://github.com/vivarium-collective/vivarium-chemotaxis
Author: Eran Agmon, Ryan Spangler
Author-email: eagmon@stanford.edu, ryan.spangler@gmail.com
License: MIT
Platform: UNKNOWN
